tests/__init__.py
tinyrouter/__init__.py
tinyrouter/helpers.py
tinyrouter/router.py
tinyrouter-0.2.1.dist-info/LICENSE
tinyrouter-0.2.1.dist-info/METADATA
tinyrouter-0.2.1.dist-info/WHEEL
tinyrouter-0.2.1.dist-info/top_level.txt
tinyrouter-0.2.1.dist-info/RECORD
