Metadata-Version: 2.1
Name: tinyrouter
Version: 0.2.1
Summary: UNKNOWN
Home-page: https://github.com/tcantalice/tinyrouter
Author: Tarcisio Cantalice
Author-email: tarcisiocantalice@gmail.com
License: MIT
Platform: UNKNOWN
Classifier: Framework :: Flask
Classifier: License :: OSI Approved :: MIT License
Classifier: Programming Language :: Python :: 3
Classifier: Programming Language :: Python :: 3.7
Requires-Dist: flask
